{"_default": {"1": {"symbol": "LMC", "score": 1742, "name": "lomocoin", "created": "1504365975"}, "2": {"symbol": "LMC", "score": 19, "name": "lomocoin", "created": "1504369333"}, "3": {"symbol": "LMC", "score": 107, "name": "lomocoin", "created": "1504376053"}, "4": {"symbol": "LMC", "score": 140, "name": "lomocoin", "created": "1504386064"}, "5": {"symbol": "LMC", "score": 30, "name": "lomocoin", "created": "1504442975"}, "6": {"symbol": "LMC", "score": 172, "name": "lomocoin", "created": "1504446344"}, "7": {"symbol": "LMC", "score": 179, "name": "lomocoin", "created": "1504540243"}, "8": {"symbol": "LMC", "score": 180, "name": "lomocoin", "created": "1504547120"}, "9": {"symbol": "LMC", "score": 143, "name": "lomocoin", "created": "1504554299"}, "10": {"symbol": "LMC", "score": 173, "name": "lomocoin", "created": "1504560885"}, "11": {"symbol": "LMC", "score": 172, "name": "lomocoin", "created": "1504567616"}, "12": {"symbol": "LMC", "score": 180, "name": "lomocoin", "created": "1504574348"}, "13": {"symbol": "LMC", "score": 180, "name": "lomocoin", "created": "1504581074"}, "14": {"symbol": "LMC", "score": 148, "name": "lomocoin", "created": "1504594547"}, "15": {"symbol": "LMC", "score": 26, "name": "lomocoin", "created": "1504601283"}, "16": {"symbol": "LMC", "score": 444, "name": "lomocoin", "created": "1504604659"}, "17": {"symbol": "LMC", "score": 1169, "name": "lomocoin", "created": "1504608031"}, "18": {"symbol": "LMC", "score": 372, "name": "lomocoin", "created": "1504611415"}, "19": {"symbol": "LMC", "score": 210, "name": "lomocoin", "created": "1504621609"}, "20": {"symbol": "LMC", "score": 180, "name": "lomocoin", "created": "1504635065"}, "21": {"symbol": "LMC", "score": 149, "name": "lomocoin", "created": "1504638458"}, "22": {"symbol": "LMC", "score": 987, "name": "lomocoin", "created": "1504648722"}, "23": {"symbol": "LMC", "score": 1119, "name": "lomocoin", "created": "1504652113"}, "24": {"symbol": "LMC", "score": 16, "name": "lomocoin", "created": "1504679306"}, "25": {"symbol": "LMC", "score": 579, "name": "lomocoin", "created": "1504696358"}, "26": {"symbol": "LMC", "score": 116, "name": "lomocoin", "created": "1504706623"}, "27": {"symbol": "LMC", "score": 1724, "name": "lomocoin", "created": "1504710046"}, "28": {"symbol": "LMC", "score": 1696, "name": "lomocoin", "created": "1504718823"}, "29": {"symbol": "LMC", "score": 685, "name": "lomocoin", "created": "1504749531"}, "30": {"symbol": "LMC", "score": 286, "name": "lomocoin", "created": "1504752845"}, "31": {"symbol": "LMC", "score": 1511, "name": "lomocoin", "created": "1504759484"}, "32": {"symbol": "LMC", "score": 1464, "name": "lomocoin", "created": "1504766128"}}}